{
  "kursus": [
    {
      "id": "pelajaran1",
      "nama": "Pelajaran 1",
      "gambar": "img1-1.svg",
      "deskripsi": "Huruf Hijaiyah",
      "huruf": [
        {
          "id": "alif1",
          "nama": "ا",
          "color": "[#663200]",
          "hover": "[#924C07]",
          "audio": "https://storage.googleapis.com/qolami-web/pelajaran1-huruf-hijaiyah/audio/1-Alif.m4a"
        },
        {
          "id": "ba1",
          "nama": "ب",
          "color": "[#663200]",
          "hover": "[#924C07]",
          "audio": "https://storage.googleapis.com/qolami-web/pelajaran1-huruf-hijaiyah/audio/2-Ba.m4a"
        },
        {
          "id": "ta1",
          "nama": "ت",
          "color": "[#663200]",
          "hover": "[#924C07]",
          "audio": "https://storage.googleapis.com/qolami-web/pelajaran1-huruf-hijaiyah/audio/3-Ta.m4a"
        },
        {
          "id": "tsa1",
          "nama": "ث",
          "color": "[#663200]",
          "hover": "[#924C07]",
          "audio": "https://storage.googleapis.com/qolami-web/pelajaran1-huruf-hijaiyah/audio/4-Tsa.m4a"
        },
        {
          "id": "jim1",
          "nama": "ج",
          "color": "[#663200]",
          "hover": "[#924C07]",
          "audio": "https://storage.googleapis.com/qolami-web/pelajaran1-huruf-hijaiyah/audio/5-Jim.m4a"
        },
        {
          "id": "ha1",
          "nama": "ح",
          "color": "[#CC6601]",
          "hover": "[#F69536]",
          "audio": "https://storage.googleapis.com/qolami-web/pelajaran1-huruf-hijaiyah/audio/6-Ha.m4a"
        },
        {
          "id": "kha1",
          "nama": "خ",
          "color": "[#CC6601]",
          "hover": "[#F69536]",
          "audio": "https://storage.googleapis.com/qolami-web/pelajaran1-huruf-hijaiyah/audio/7-Kho.m4a"
        },
        {
          "id": "dal1",
          "nama": "د",
          "color": "[#CC6601]",
          "hover": "[#F69536]",
          "audio": "https://storage.googleapis.com/qolami-web/pelajaran1-huruf-hijaiyah/audio/8-Dal.m4a"
        },
        {
          "id": "dzal1",
          "nama": "ذ",
          "color": "[#CC6601]",
          "hover": "[#F69536]",
          "audio": "https://storage.googleapis.com/qolami-web/pelajaran1-huruf-hijaiyah/audio/9-Dzal.m4a"
        },
        {
          "id": "ra1",
          "nama": "ر",
          "color": "[#CC6601]",
          "hover": "[#F69536]",
          "audio": "https://storage.googleapis.com/qolami-web/pelajaran1-huruf-hijaiyah/audio/10-Ra.m4a"
        },
        {
          "id": "za1",
          "nama": "ز",
          "color": "[#1F4E78]",
          "hover": "[#388AD4]"
        },
        {
          "id": "sin1",
          "nama": "س",
          "color": "[#1F4E78]",
          "hover": "[#388AD4]"
        },
        {
          "id": "syin1",
          "nama": "ش",
          "color": "[#1F4E78]",
          "hover": "[#388AD4]"
        },
        {
          "id": "shad1",
          "nama": "ص",
          "color": "[#1F4E78]",
          "hover": "[#388AD4]"
        },
        {
          "id": "dhad1",
          "nama": "ض",
          "color": "[#1F4E78]",
          "hover": "[#388AD4]"
        },
        {
          "id": "tha1",
          "nama": "ط",
          "color": "[#009900]",
          "hover": "[#06D805]"
        },
        {
          "id": "zha1",
          "nama": "ظ",
          "color": "[#009900]",
          "hover": "[#06D805]"
        },
        {
          "id": "ain1",
          "nama": "ع",
          "color": "[#009900]",
          "hover": "[#06D805]"
        },
        {
          "id": "ghain1",
          "nama": "غ",
          "color": "[#009900]",
          "hover": "[#06D805]"
        },
        {
          "id": "fa1",
          "nama": "ف",
          "color": "[#009900]",
          "hover": "[#06D805]"
        },
        {
          "id": "qaf1",
          "nama": "ق",
          "color": "[#7030A0]",
          "hover": "[#BB65FA]"
        },
        {
          "id": "kaf1",
          "nama": "ك",
          "color": "[#7030A0]",
          "hover": "[#BB65FA]"
        },
        {
          "id": "lam1",
          "nama": "ل",
          "color": "[#7030A0]",
          "hover": "[#BB65FA]"
        },
        {
          "id": "mim1",
          "nama": "م",
          "color": "[#7030A0]",
          "hover": "[#BB65FA]"
        },
        {
          "id": "nun1",
          "nama": "ن",
          "color": "[#7030A0]",
          "hover": "[#BB65FA]"
        },
        {
          "id": "waw1",
          "nama": "و",
          "color": "[#800000]",
          "hover": "[#FF4948]"
        },
        {
          "id": "ha1_2",
          "nama": "ه",
          "color": "[#800000]",
          "hover": "[#FF4948]"
        },
        {
          "id": "lamalif1",
          "nama": "لا",
          "color": "[#800000]",
          "hover": "[#FF4948]"
        },
        {
          "id": "hamzah1",
          "nama": "ء",
          "color": "[#800000]",
          "hover": "[#FF4948]"
        },
        {
          "id": "ya1",
          "nama": "ي",
          "color": "[#800000]",
          "hover": "[#FF4948]"
        }
      ]
    },
    {
      "id": "latihan1",
      "nama": "Latihan 1",
      "gambar": "img1-2.svg",
      "deskripsi": "Huruf Hijaiyah",
      "jenis": [
        {
          "id": "gambar1",
          "nama": "GAMBAR 1"
        },
        {
          "id": "audio1",
          "nama": "AUDIO 1"
        },
        {
          "id": "video1",
          "nama": "VIDEO 1"
        }
      ]
    },
    {
      "id": "ujian1",
      "nama": "Ujian 1",
      "gambar": "img1-3.svg",
      "deskripsi": "Huruf Hijaiyah"
    },
    {
      "id": "pelajaran2",
      "nama": "Pelajaran 2",
      "gambar": "img2-1.svg",
      "deskripsi": "Huruf Berharakat Fathah",
      "huruf": [
        {
          "id": "alif2",
          "nama": "اَ",
          "color": "[#663200]",
          "hover": "[#924C07]"
        },
        {
          "id": "ba2",
          "nama": "بَ",
          "color": "[#663200]",
          "hover": "[#924C07]"
        },
        {
          "id": "ta2",
          "nama": "تَ",
          "color": "[#663200]",
          "hover": "[#924C07]"
        },
        {
          "id": "tsa2",
          "nama": "ثَ",
          "color": "[#663200]",
          "hover": "[#924C07]"
        },
        {
          "id": "jim2",
          "nama": "جَ",
          "color": "[#663200]",
          "hover": "[#924C07]"
        },
        {
          "id": "ha2",
          "nama": "حَ",
          "color": "[#CC6601]",
          "hover": "[#F69536]"
        },
        {
          "id": "kha2",
          "nama": "خَ",
          "color": "[#CC6601]",
          "hover": "[#F69536]"
        },
        {
          "id": "dal2",
          "nama": "دَ",
          "color": "[#CC6601]",
          "hover": "[#F69536]"
        },
        {
          "id": "dzal2",
          "nama": "ذَ",
          "color": "[#CC6601]",
          "hover": "[#F69536]"
        },
        {
          "id": "ra2",
          "nama": "رَ",
          "color": "[#CC6601]",
          "hover": "[#F69536]"
        },
        {
          "id": "za2",
          "nama": "زَ",
          "color": "[#1F4E78]",
          "hover": "[#388AD4]"
        },
        {
          "id": "sin2",
          "nama": "سَ",
          "color": "[#1F4E78]",
          "hover": "[#388AD4]"
        },
        {
          "id": "syin2",
          "nama": "شَ",
          "color": "[#1F4E78]",
          "hover": "[#388AD4]"
        },
        {
          "id": "shad2",
          "nama": "صَ",
          "color": "[#1F4E78]",
          "hover": "[#388AD4]"
        },
        {
          "id": "dhad2",
          "nama": "ضَ",
          "color": "[#1F4E78]",
          "hover": "[#388AD4]"
        },
        {
          "id": "tha2",
          "nama": "طَ",
          "color": "[#009900]",
          "hover": "[#06D805]"
        },
        {
          "id": "zha2",
          "nama": "ظَ",
          "color": "[#009900]",
          "hover": "[#06D805]"
        },
        {
          "id": "ain2",
          "nama": "عَ",
          "color": "[#009900]",
          "hover": "[#06D805]"
        },
        {
          "id": "ghain2",
          "nama": "غَ",
          "color": "[#009900]",
          "hover": "[#06D805]"
        },
        {
          "id": "fa2",
          "nama": "فَ",
          "color": "[#009900]",
          "hover": "[#06D805]"
        },
        {
          "id": "qaf2",
          "nama": "قَ",
          "color": "[#7030A0]",
          "hover": "[#BB65FA]"
        },
        {
          "id": "kaf2",
          "nama": "كَ",
          "color": "[#7030A0]",
          "hover": "[#BB65FA]"
        },
        {
          "id": "lam2",
          "nama": "لَ",
          "color": "[#7030A0]",
          "hover": "[#BB65FA]"
        },
        {
          "id": "mim2",
          "nama": "مَ",
          "color": "[#7030A0]",
          "hover": "[#BB65FA]"
        },
        {
          "id": "nun2",
          "nama": "نَ",
          "color": "[#7030A0]",
          "hover": "[#BB65FA]"
        },
        {
          "id": "waw2",
          "nama": "وَ",
          "color": "[#800000]",
          "hover": "[#FF4948]"
        },
        {
          "id": "ha2_2",
          "nama": "هَ",
          "color": "[#800000]",
          "hover": "[#FF4948]"
        },
        {
          "id": "lamalif2",
          "nama": "يَ",
          "color": "[#800000]",
          "hover": "[#FF4948]"
        }
      ]
    },
    {
      "id": "latihan2",
      "nama": "Latihan 2",
      "gambar": "img2-2.svg",
      "deskripsi": "Huruf Berharakat Fathah",
      "jenis": [
        {
          "id": "gambar2",
          "nama": "GAMBAR 2"
        },
        {
          "id": "audio2",
          "nama": "AUDIO 2"
        },
        {
          "id": "video2",
          "nama": "VIDEO 2"
        }
      ]
    },
    {
      "id": "ujian2",
      "nama": "Ujian 2",
      "gambar": "img2-3.svg",
      "deskripsi": "Huruf Berharakat Fathah"
    },
    {
      "id": "pelajaran3",
      "nama": "Pelajaran 3",
      "gambar": "img3-1.svg",
      "deskripsi": "Huruf Berharakat Dhammah",
      "huruf": [
        {
          "id": "alif1",
          "nama": "ا",
          "color": "[#663200]",
          "hover": "[#924C07]"
        },
        {
          "id": "ba1",
          "nama": "ب",
          "color": "[#663200]",
          "hover": "[#924C07]"
        },
        {
          "id": "ta1",
          "nama": "ت",
          "color": "[#663200]",
          "hover": "[#924C07]"
        },
        {
          "id": "tsa1",
          "nama": "ث",
          "color": "[#663200]",
          "hover": "[#924C07]"
        },
        {
          "id": "jim1",
          "nama": "ج",
          "color": "[#663200]",
          "hover": "[#924C07]"
        },
        {
          "id": "ha1",
          "nama": "ح",
          "color": "[#CC6601]",
          "hover": "[#F69536]"
        },
        {
          "id": "kha1",
          "nama": "خ",
          "color": "[#CC6601]",
          "hover": "[#F69536]"
        },
        {
          "id": "dal1",
          "nama": "د",
          "color": "[#CC6601]",
          "hover": "[#F69536]"
        },
        {
          "id": "dzal1",
          "nama": "ذ",
          "color": "[#CC6601]",
          "hover": "[#F69536]"
        },
        {
          "id": "ra1",
          "nama": "ر",
          "color": "[#CC6601]",
          "hover": "[#F69536]"
        },
        {
          "id": "za1",
          "nama": "ز",
          "color": "[#1F4E78]",
          "hover": "[#388AD4]"
        },
        {
          "id": "sin1",
          "nama": "س",
          "color": "[#1F4E78]",
          "hover": "[#388AD4]"
        },
        {
          "id": "syin1",
          "nama": "ش",
          "color": "[#1F4E78]",
          "hover": "[#388AD4]"
        },
        {
          "id": "shad1",
          "nama": "ص",
          "color": "[#1F4E78]",
          "hover": "[#388AD4]"
        },
        {
          "id": "dhad1",
          "nama": "ض",
          "color": "[#1F4E78]",
          "hover": "[#388AD4]"
        },
        {
          "id": "tha1",
          "nama": "ط",
          "color": "[#009900]",
          "hover": "[#06D805]"
        },
        {
          "id": "zha1",
          "nama": "ظ",
          "color": "[#009900]",
          "hover": "[#06D805]"
        },
        {
          "id": "ain1",
          "nama": "ع",
          "color": "[#009900]",
          "hover": "[#06D805]"
        },
        {
          "id": "ghain",
          "nama": "غ",
          "color": "[#009900]",
          "hover": "[#06D805]"
        },
        {
          "id": "fa1",
          "nama": "ف",
          "color": "[#009900]",
          "hover": "[#06D805]"
        },
        {
          "id": "qaf1",
          "nama": "ق",
          "color": "[#7030A0]",
          "hover": "[#BB65FA]"
        },
        {
          "id": "kaf1",
          "nama": "ك",
          "color": "[#7030A0]",
          "hover": "[#BB65FA]"
        },
        {
          "id": "lam1",
          "nama": "ل",
          "color": "[#7030A0]",
          "hover": "[#BB65FA]"
        },
        {
          "id": "mim1",
          "nama": "م",
          "color": "[#7030A0]",
          "hover": "[#BB65FA]"
        },
        {
          "id": "nun1",
          "nama": "ن",
          "color": "[#7030A0]",
          "hover": "[#BB65FA]"
        },
        {
          "id": "waw1",
          "nama": "و",
          "color": "[#800000]",
          "hover": "[#FF4948]"
        },
        {
          "id": "ha1_2",
          "nama": "ه",
          "color": "[#800000]",
          "hover": "[#FF4948]"
        },
        {
          "id": "lamalif1",
          "nama": "لا",
          "color": "[#800000]",
          "hover": "[#FF4948]"
        },
        {
          "id": "hamzah1",
          "nama": "ء",
          "color": "[#800000]",
          "hover": "[#FF4948]"
        },
        {
          "id": "ya1",
          "nama": "ي",
          "color": "[#800000]",
          "hover": "[#FF4948]"
        }
      ]
    },
    {
      "id": "latihan3",
      "nama": "Latihan 3",
      "gambar": "img3-2.svg",
      "deskripsi": "Huruf Berharakat Dhammah",
      "jenis": [
        {
          "id": "gambar3",
          "nama": "GAMBAR 3"
        },
        {
          "id": "audio3",
          "nama": "AUDIO 3"
        },
        {
          "id": "video3",
          "nama": "VIDEO 3"
        }
      ]
    },
    {
      "id": "ujian3",
      "nama": "Ujian 3",
      "gambar": "img3-3.svg",
      "deskripsi": "Huruf Berharakat Dhammah"
    }
  ],
  "pengguna": [
    {
      "id": "1712828076700",
      "namaDepan": "asss",
      "namaBelakang": "sssss",
      "email": "rizal@gmail.com",
      "password": "asdasdadsdadads",
      "gambarProfile": "",
      "token": "yeCwuqiH5cJ4wUJyWk7ZV9kdHonexynwVvBBrvuZwz.aM0nJKLvxscpuYfls7igibybMcVHmuJbefFx9SmRooYcVbR6mGKpbewdg"
    },
    {
      "id": "1712971068083",
      "namaDepan": "sasasa",
      "namaBelakang": "aaa",
      "email": "hiro@gmail.com",
      "password": "hirohirohiro",
      "gambarProfile": {},
      "token": "JSR92ZJYRaeB.Z2.7NwUnuh0KqWtQ8kJMbAIBBFzcdmFjoCpWSM8SNdbeJcA.ksgtqrnzM2wROlaPDgPusw7pT73YKVMPzfnlWlr"
    },
    {
      "id": "1713048105270",
      "namaDepan": "sada",
      "namaBelakang": "dddad",
      "email": "hiro@gmail.com",
      "password": "ujosdbfsiodfadfd",
      "gambarProfile": "",
      "token": "iMYfCIJPl7C6Td32sHUUIrquRn0EDZXAFmI3Cz7ThhZnCLhzSzejCDNUW.heXDgc82iKXRQ0xwEv0BdU.txAJxlsIWSvDZjPS.Pc"
    },
    {
      "id": "1713279710754",
      "namaDepan": "sdfsdfs",
      "namaBelakang": "sdfsfdf",
      "email": "hiro@gmail.com",
      "password": "hirohirohiro",
      "gambarProfile": "cardabout_2.svg",
      "token": "JSR92ZJYRaeB.Z2.7NwUnuh0KqWtQ8kJMbAIBBFzcdmFjoCpWSM8SNdbeJcA.ksgtqrnzM2wROlaPDgPusw7pT73YKVMPzfnlWlr"
    },
    {
      "id": "1713798651120",
      "namaDepan": "angga",
      "namaBelakang": "aditya",
      "email": "angga@gmail.com",
      "password": "anggaangga",
      "gambarProfile": "profile.jpeg",
      "token": null
    },
    {
      "id": "1713798801196",
      "namaDepan": "aaaa",
      "namaBelakang": "aaaaa",
      "email": "aaa@gmail.com",
      "password": "aaaaaaaaa",
      "gambarProfile": "profile.jpeg",
      "token": null
    },
    {
      "id": "1713800617706",
      "namaDepan": "asdad",
      "namaBelakang": "asasdsdasd",
      "email": "asdada@gmail.com",
      "password": "dskfnsodafdafdsf",
      "gambarProfile": "profile.jpeg",
      "token": null
    },
    {
      "id": "1713802224476",
      "namaDepan": "fdgdfgdfgdfg",
      "namaBelakang": "fdgdfgdfgdg",
      "email": "hhf@gmail.com",
      "password": "fsgfdgfdgdfg",
      "gambarProfile": "profile.jpeg",
      "token": null
    },
    {
      "id": "1713802396915",
      "namaDepan": "aadadadad",
      "namaBelakang": "adsadadad",
      "email": "saas@gmail.com",
      "password": "ddsfdsdfsdfs",
      "gambarProfile": "profile.jpeg",
      "token": null
    },
    {
      "id": "1713827404977",
      "namaDepan": "sdsd",
      "namaBelakang": "sdsdsd",
      "email": "dws@gmail.com",
      "password": "ksdfnsuofsdfsfsdf",
      "gambarProfile": "profile.jpeg",
      "token": null
    },
    {
      "id": "1713827459427",
      "namaDepan": "sdfsdfsf",
      "namaBelakang": "sdfdsfds",
      "email": "fsfsdfsdf@gmail.com",
      "password": "fdssdfsddsffsdsfd",
      "gambarProfile": "profile.jpeg",
      "token": null
    },
    {
      "id": "1713827517358",
      "namaDepan": "asdasda",
      "namaBelakang": "dsadadas",
      "email": "sda@gmail.com",
      "password": "sdhifbsyfsfsd",
      "gambarProfile": "profile.jpeg",
      "token": null
    },
    {
      "id": "1713827826112",
      "namaDepan": "asdasd",
      "namaBelakang": "adasdadsdsa",
      "email": "asd@gmail.com",
      "password": "kslvnsfsfdf",
      "gambarProfile": "profile.jpeg",
      "token": null
    },
    {
      "id": "1713827857870",
      "namaDepan": "sdfsdfsdfs",
      "namaBelakang": "dfsfsff",
      "email": "sfsdf@gmail.com",
      "password": "dsfsfsfsfdfsdffd",
      "gambarProfile": "profile.jpeg",
      "token": null
    },
    {
      "id": "1713828220563",
      "namaDepan": "sdfsdf",
      "namaBelakang": "sdfsdfsdfs",
      "email": "dfdf@gmail.com",
      "password": "dsffsddsf",
      "gambarProfile": "profile.jpeg",
      "token": null
    },
    {
      "id": "1713829114491",
      "namaDepan": "asdasd",
      "namaBelakang": "asdasdasdas",
      "email": "dsad@gmail.com",
      "password": "jdsfnuifsfsdf",
      "gambarProfile": "profile.jpeg",
      "token": null
    },
    {
      "id": "1713863865978",
      "namaDepan": "dsfdsfsfs",
      "namaBelakang": "fsdf",
      "email": "dfs@gmailc.com",
      "password": "sfvsfsfdfsdfs",
      "gambarProfile": "profile.jpeg",
      "token": null
    }
  ],
  "detailPelajaran": [
    {
      "id": "alif2",
      "judul": "Pelajaran 2",
      "nama": "Alif Berharakat Fathah",
      "video": "asdasdad",
      "gambar": "img1-1.svg",
      "detail1": "Huruf Alif",
      "detail2": "biru",
      "detail3": "harakat fathah"
    },
    {
      "id": "ba2",
      "judul": "Pelajaran 2",
      "nama": "Ba Berharakat Fathah",
      "video": "asdasdad",
      "gambar": "img1-1.svg",
      "detail1": "Huruf Ba",
      "detail2": "biru",
      "detail3": "harakat fathah"
    },
    {
      "id": "ta2",
      "judul": "Pelajaran 2",
      "nama": "Ta Berharakat Fathah",
      "video": "asdasdad",
      "gambar": "img1-1.svg",
      "detail1": "Huruf Ta",
      "detail2": "biru",
      "detail3": "harakat fathah"
    },
    {
      "id": "alif3",
      "judul": "Pelajaran 3",
      "nama": "Alif Huruf Berharakat Dhammah",
      "video": "asdasdad",
      "gambar": "img1-1.svg",
      "detail1": "Huruf Alif",
      "detail2": "biru",
      "detail3": "huruf berharakat dhammah"
    },
    {
      "id": "ba3",
      "judul": "Pelajaran 3",
      "nama": "Ba Huruf Berharakat Dhammah",
      "video": "asdasdad",
      "gambar": "img1-1.svg",
      "detail1": "Huruf Ba",
      "detail2": "biru",
      "detail3": "huruf berharakat dhammah"
    },
    {
      "id": "ta3",
      "judul": "Pelajaran 3",
      "nama": "Ta Huruf Berharakat Dhammah",
      "video": "asdasdad",
      "gambar": "img1-1.svg",
      "detail1": "Huruf Ta",
      "detail2": "biru",
      "detail3": "huruf berharakat dhammah"
    }
  ],
  "detailLatihan": [
    {
      "id": "gambar1",
      "judul": "LATIHAN GAMBAR 1"
    },
    {
      "id": "audio1",
      "judul": "LATIHAN AUDIO 1"
    },
    {
      "id": "video1",
      "judul": "LATIHAN VIDEO 1"
    },
    {
      "id": "gambar1",
      "judul": "GAMBAR 1"
    },
    {
      "id": "audio2",
      "judul": "AUDIO 2"
    },
    {
      "id": "video2",
      "judul": "VIDEO 2"
    },
    {
      "id": "gambar3",
      "judul": "GAMBAR 3"
    },
    {
      "id": "audio3",
      "judul": "AUDIO 3"
    },
    {
      "id": "video3",
      "judul": "VIDEO 3"
    }
  ],
  "detailUjian": [
    {
      "id": "ujian1",
      "judul": "UJIAN 1"
    },
    {
      "id": "ujian2",
      "judul": "UJIAN 2"
    },
    {
      "id": "ujian3",
      "judul": "UJIAN 3"
    }
  ]
}